Mohit_STT/__init__.py
Mohit_STT-0.1.dist-info/METADATA
Mohit_STT-0.1.dist-info/WHEEL
Mohit_STT-0.1.dist-info/top_level.txt
Mohit_STT-0.1.dist-info/RECORD
