Metadata-Version: 2.1
Name: Mohit_STT
Version: 0.1
Summary: This is speech to text package created by Mohit Kumar
Author: Mohit Kumar
Author-email: megamohit2006@gmail.com
